housing_data_5507/ingest_data.py
housing_data_5507/nonstandardcode.py
housing_data_5507/score.py
housing_data_5507/train.py
housing_library_5507-0.2.dist-info/METADATA
housing_library_5507-0.2.dist-info/WHEEL
housing_library_5507-0.2.dist-info/entry_points.txt
housing_library_5507-0.2.dist-info/top_level.txt
housing_library_5507-0.2.dist-info/RECORD
