Metadata-Version: 2.1
Name: housing-library-5507
Version: 0.2
Summary: Sample code for coding practice
Author-email: 5507lohithareddy <lohitha.reddy@tigeranalytics.com>
Project-URL: Homepage, https://github.com/5507lohithareddy/mle-training
Keywords: housing,data training
Classifier: Programming Language :: Python :: 3
Requires-Python: >=3.11
Requires-Dist: numpy
Requires-Dist: pandas
Requires-Dist: scikit-learn
